{
  "top_by_psi": [
    {
      "feature": "hostname_length",
      "ks": 0.001422212283552049,
      "psi": 2.9174153535590897e-05,
      "train_mean": 19.252546310424805,
      "test_mean": 19.2612247467041
    },
    {
      "feature": "entropy",
      "ks": 0.0015222960512597528,
      "psi": 2.309033831790286e-05,
      "train_mean": 4.285727500915527,
      "test_mean": 4.285444736480713
    },
    {
      "feature": "url_length",
      "ks": 0.0011446818398559433,
      "psi": 2.1064047145389582e-05,
      "train_mean": 46.6224479675293,
      "test_mean": 46.601715087890625
    },
    {
      "feature": "num_tokens",
      "ks": 0.0008785757079020629,
      "psi": 1.809025823520598e-05,
      "train_mean": 7.667129039764404,
      "test_mean": 7.66696310043335
    },
    {
      "feature": "path_length",
      "ks": 0.0011870810998572956,
      "psi": 1.7289134354811815e-05,
      "train_mean": 15.187427520751953,
      "test_mean": 15.1836519241333
    },
    {
      "feature": "domain_url_ratio",
      "ks": 0.001320470759875958,
      "psi": 1.4685234640529255e-05,
      "train_mean": 0.4444904029369354,
      "test_mean": 0.444776713848114
    },
    {
      "feature": "dot_count",
      "ks": 0.0011439748000470207,
      "psi": 6.693047274730558e-06,
      "train_mean": 2.2372851371765137,
      "test_mean": 2.2392518520355225
    },
    {
      "feature": "query_length",
      "ks": 0.0008634524134794042,
      "psi": 4.087768145220515e-06,
      "train_mean": 4.513997554779053,
      "test_mean": 4.488056182861328
    },
    {
      "feature": "digit_count",
      "ks": 0.0006811468997388603,
      "psi": 3.84782639155003e-06,
      "train_mean": 1.508471131324768,
      "test_mean": 1.5033687353134155
    },
    {
      "feature": "equal_count",
      "ks": 0.0006352717388016238,
      "psi": 1.1958602057218523e-06,
      "train_mean": 0.25512731075286865,
      "test_mean": 0.25385186076164246
    },
    {
      "feature": "digit_alphabet_ratio",
      "ks": 0.0008107805521790912,
      "psi": 7.68666889372439e-09,
      "train_mean": 0.04582229629158974,
      "test_mean": 0.04554400220513344
    },
    {
      "feature": "special_char_alphabet_ratio",
      "ks": 0.0006770445213502008,
      "psi": 0.0,
      "train_mean": 0.0017973260255530477,
      "test_mean": 0.001786001375876367
    },
    {
      "feature": "https_in_url",
      "ks": 0.000670045669562469,
      "psi": 0.0,
      "train_mean": 0.5408260822296143,
      "test_mean": 0.5414961576461792
    },
    {
      "feature": "special_char_count",
      "ks": 0.0006352717388016238,
      "psi": 0.0,
      "train_mean": 0.12747794389724731,
      "test_mean": 0.12656718492507935
    },
    {
      "feature": "ampersand_count",
      "ks": 0.0006352717388016238,
      "psi": 0.0,
      "train_mean": 0.12747794389724731,
      "test_mean": 0.12656718492507935
    },
    {
      "feature": "dash_count",
      "ks": 0.0005610200910365348,
      "psi": 0.0,
      "train_mean": 0.10802078992128372,
      "test_mean": 0.10699473321437836
    },
    {
      "feature": "question_mark_count",
      "ks": 0.0003646951041165192,
      "psi": 0.0,
      "train_mean": 0.12764938175678253,
      "test_mean": 0.1272846758365631
    },
    {
      "feature": "js_used",
      "ks": 0.0001224952580444194,
      "psi": 0.0,
      "train_mean": 0.0013800009619444609,
      "test_mean": 0.0015024961903691292
    },
    {
      "feature": "ip_as_hostname",
      "ks": 4.301803211081978e-05,
      "psi": 0.0,
      "train_mean": 0.05008789151906967,
      "test_mean": 0.05004487559199333
    },
    {
      "feature": "css_used",
      "ks": 1.749976339326942e-05,
      "psi": 0.0,
      "train_mean": 6.0000042140018195e-05,
      "test_mean": 7.749980431981385e-05
    }
  ],
  "psi_guidance": "PSI <0.1 stable; 0.1\u20130.25 moderate; >0.25 major shift",
  "ks_guidance": "KS <0.1 small; 0.1\u20130.2 moderate; >0.2 large"
}